{
    "project_name": "20233_02_03_Entrees_Sorties",
    "functions": [
        {
            "function_name": "main",
            "function_code": "int main(void) {\n    int age;\n\n    printf(\"Saisir votre age: \");\n    scanf(\"%i\", &age);\n\n    printf(\"L'age que vous avez saisi est: %i\\n\", age);\n\n\n    return 0;\n}",
            "function_ast": "FuncDef(\n  decl=\n    Decl(\n      name='main',\n      quals=[],\n      align=[],\n      storage=[],\n      funcspec=[],\n      type=\n        FuncDecl(\n          args=\n            ParamList(\n              params[0]=\n                Typename(\n                  name=None,\n                  quals=[],\n                  align=None,\n                  type=\n                    TypeDecl(\n                      declname=None,\n                      quals=[],\n                      align=None,\n                      type=\n                        IdentifierType(\n                          names=['void'],\n                        )\n                    )\n                )\n            )\n          type=\n            TypeDecl(\n              declname='main',\n              quals=[],\n              align=None,\n              type=\n                IdentifierType(\n                  names=['int'],\n                )\n            )\n        )\n    )\n  body=\n    Compound(\n      block_items[0]=\n        Decl(\n          name='age',\n          quals=[],\n          align=[],\n          storage=[],\n          funcspec=[],\n          type=\n            TypeDecl(\n              declname='age',\n              quals=[],\n              align=None,\n              type=\n                IdentifierType(\n                  names=['int'],\n                )\n            )\n        )\n      block_items[1]=\n        FuncCall(\n          name=\n            ID(\n              name='printf',\n            )\n          args=\n            ExprList(\n              exprs[0]=\n                Constant(\n                  type='string',\n                  value='\"Saisir votre age: \"',\n                )\n            )\n        )\n      block_items[2]=\n        FuncCall(\n          name=\n            ID(\n              name='scanf',\n            )\n          args=\n            ExprList(\n              exprs[0]=\n                Constant(\n                  type='string',\n                  value='\"%i\"',\n                )\n              exprs[1]=\n                UnaryOp(\n                  op='&',\n                  expr=\n                    ID(\n                      name='age',\n                    )\n                )\n            )\n        )\n      block_items[3]=\n        FuncCall(\n          name=\n            ID(\n              name='printf',\n            )\n          args=\n            ExprList(\n              exprs[0]=\n                Constant(\n                  type='string',\n                  value='\"L\\'age que vous avez saisi est: %i\\\\n\"',\n                )\n              exprs[1]=\n                ID(\n                  name='age',\n                )\n            )\n        )\n      block_items[4]=\n        Return(\n          expr=\n            Constant(\n              type='int',\n              value='0',\n            )\n        )\n    )\n)"
        }
    ]
}